odoo/addons/budget_control_request_document/README.rst
odoo/addons/budget_control_request_document/__init__.py
odoo/addons/budget_control_request_document/__manifest__.py
odoo/addons/budget_control_request_document/hooks.py
odoo/addons/budget_control_request_document/models/__init__.py
odoo/addons/budget_control_request_document/models/budget_control.py
odoo/addons/budget_control_request_document/models/budget_period.py
odoo/addons/budget_control_request_document/models/request_budget_move.py
odoo/addons/budget_control_request_document/models/request_document.py
odoo/addons/budget_control_request_document/models/request_order.py
odoo/addons/budget_control_request_document/readme/CONTRIBUTORS.md
odoo/addons/budget_control_request_document/readme/DESCRIPTION.md
odoo/addons/budget_control_request_document/report/__init__.py
odoo/addons/budget_control_request_document/report/budget_common_monitoring.py
odoo/addons/budget_control_request_document/report/budget_monitor_report.py
odoo/addons/budget_control_request_document/security/ir.model.access.csv
odoo/addons/budget_control_request_document/static/description/icon.png
odoo/addons/budget_control_request_document/static/description/index.html
odoo/addons/budget_control_request_document/tests/__init__.py
odoo/addons/budget_control_request_document/tests/request_document_tester.py
odoo/addons/budget_control_request_document/tests/test_budget_control_request_document.py
odoo/addons/budget_control_request_document/views/budget_control_view.xml
odoo/addons/budget_control_request_document/views/budget_period_view.xml
odoo/addons/budget_control_request_document/views/request_document_view.xml
odoo/addons/budget_control_request_document/views/request_order_view.xml
odoo_addon_budget_control_request_document-18.0.1.1.1.dist-info/METADATA
odoo_addon_budget_control_request_document-18.0.1.1.1.dist-info/WHEEL
odoo_addon_budget_control_request_document-18.0.1.1.1.dist-info/top_level.txt
odoo_addon_budget_control_request_document-18.0.1.1.1.dist-info/RECORD
